MANIFEST.in
requirements.txt
setup.py
config/config.json
config/config_testing.json
data/map_par.pkl
data/mh_par.pkl
data/test_trace.csv
invivoinfer/__init__.py
invivoinfer/infer.py
invivoinfer/mc_functions.py
invivoinfer/plot_scripts.py
invivoinfer/pyprocess.py
invivoinfer/signalproc_functions.py
invivoinfer/vc_gen_class.py
invivoinfer/vc_infer_rawdata.py
invivoinfer/vc_infer_trace.py
invivoinfer.egg-info/PKG-INFO
invivoinfer.egg-info/SOURCES.txt
invivoinfer.egg-info/dependency_links.txt
invivoinfer.egg-info/not-zip-safe
invivoinfer.egg-info/requires.txt
invivoinfer.egg-info/top_level.txt
notebooks/Example_analysis.ipynb