Metadata-Version: 1.0
Name: invivoinfer
Version: 0.1.1
Summary: invivoinfer, code described in the paper "Extraction of synaptic input properties in vivo",P.Puggioni et al.
Home-page: https://github.com/ppuggioni/invivoinfer
Author: Paolo Puggioni
Author-email: p.paolo321@gmail.com
License: MIT
Platform: UNKNOWN
